nanocamera/NanoCam.py
nanocamera/__init__.py
nanocamera-0.1.5.dist-info/LICENSE
nanocamera-0.1.5.dist-info/METADATA
nanocamera-0.1.5.dist-info/WHEEL
nanocamera-0.1.5.dist-info/top_level.txt
nanocamera-0.1.5.dist-info/RECORD
