Metadata-Version: 2.1
Name: nanocamera
Version: 0.1.5
Summary: A Python camera interface for the Jetson Nano
Home-page: https://github.com/thehapyone/NanoCamera
Author: Ayo Ayibiowu
Author-email: charlesayibiowu@hotmail.com
License: UNKNOWN
Project-URL: Examples, https://github.com/thehapyone/NanoCamera/tree/master/examples
Project-URL: Documentation, https://github.com/thehapyone/NanoCamera/blob/master/README.md
Project-URL: Source Code, https://github.com/thehapyone/NanoCamera
Platform: UNKNOWN
Classifier: Programming Language :: Python :: 3
Classifier: License :: OSI Approved :: MIT License
Classifier: Operating System :: POSIX :: Linux
Requires-Python: >=3
